pywatershed/__init__.py
pywatershed/constants.py
pywatershed/version.py
pywatershed/analysis/__init__.py
pywatershed/analysis/model_graph.py
pywatershed/analysis/process_plot.py
pywatershed/analysis/utils/__init__.py
pywatershed/analysis/utils/colorbrewer.py
pywatershed/atmosphere/__init__.py
pywatershed/atmosphere/prms_atmosphere.py
pywatershed/atmosphere/prms_solar_geometry.py
pywatershed/atmosphere/solar_constants.py
pywatershed/base/__init__.py
pywatershed/base/accessor.py
pywatershed/base/adapter.py
pywatershed/base/budget.py
pywatershed/base/conservative_process.py
pywatershed/base/control.py
pywatershed/base/data_model.py
pywatershed/base/flow_graph.py
pywatershed/base/meta.py
pywatershed/base/model.py
pywatershed/base/parameters.py
pywatershed/base/process.py
pywatershed/base/timeseries.py
pywatershed/data/big_sandy_starfit_parameters.nc
pywatershed/data/drb_2yr/dprst_seep_hru.nc
pywatershed/data/drb_2yr/drb_2yr_gage_poi_obs.nc
pywatershed/data/drb_2yr/myparam.param
pywatershed/data/drb_2yr/nhm.control
pywatershed/data/drb_2yr/parameters_PRMSAtmosphere.nc
pywatershed/data/drb_2yr/parameters_PRMSCanopy.nc
pywatershed/data/drb_2yr/parameters_PRMSChannel.nc
pywatershed/data/drb_2yr/parameters_PRMSGroundwater.nc
pywatershed/data/drb_2yr/parameters_PRMSRunoff.nc
pywatershed/data/drb_2yr/parameters_PRMSSnow.nc
pywatershed/data/drb_2yr/parameters_PRMSSoilzone.nc
pywatershed/data/drb_2yr/parameters_PRMSSolarGeometry.nc
pywatershed/data/drb_2yr/parameters_dis_both.nc
pywatershed/data/drb_2yr/parameters_dis_hru.nc
pywatershed/data/drb_2yr/parameters_dis_seg.nc
pywatershed/data/drb_2yr/prcp.cbh
pywatershed/data/drb_2yr/prcp.nc
pywatershed/data/drb_2yr/soil_to_gw.nc
pywatershed/data/drb_2yr/ssr_to_gw.nc
pywatershed/data/drb_2yr/tmax.cbh
pywatershed/data/drb_2yr/tmax.nc
pywatershed/data/drb_2yr/tmin.cbh
pywatershed/data/drb_2yr/tmin.nc
pywatershed/hydrology/__init__.py
pywatershed/hydrology/obsin_flow_node.py
pywatershed/hydrology/pass_through_flow_node.py
pywatershed-2.0.2.dist-info/LICENSE
pywatershed-2.0.2.dist-info/METADATA
pywatershed-2.0.2.dist-info/WHEEL
pywatershed-2.0.2.dist-info/top_level.txt
pywatershed-2.0.2.dist-info/RECORD
