Metadata-Version: 2.2
Name: pywatershed
Version: 2.0.2
Summary: pywatershed is a Python package for hydrologic modeling
Author-email: USGS Enterprise Capacity Team <modflow@usgs.gov>
Maintainer-email: "James L. McCreight" <jmccreight@usgs.gov>, "Joseph D. Hughes" <jdhughes@usgs.gov>
License: CC0
Project-URL: Documentation, https://pywatershed.readthedocs.io
Project-URL: Bug Tracker, https://github.com/EC-USGS/pywatershed/issues
Project-URL: Source Code, https://github.com/EC-USGS/pywatershed
Keywords: hydrology,PRMS
Classifier: Development Status :: 5 - Production/Stable
Classifier: Intended Audience :: Science/Research
Classifier: License :: CC0 1.0 Universal (CC0 1.0) Public Domain Dedication
Classifier: Programming Language :: Python :: 3 :: Only
Classifier: Programming Language :: Python :: 3.9
Classifier: Programming Language :: Python :: 3.10
Classifier: Topic :: Scientific/Engineering :: Hydrology
Requires-Python: <3.12,>=3.10
License-File: LICENSE
Requires-Dist: contextily
Requires-Dist: numpy>=2.0.0
Requires-Dist: matplotlib>=1.4.0
Requires-Dist: epiweeks
Requires-Dist: flopy
Requires-Dist: geopandas
Requires-Dist: netCDF4
Requires-Dist: networkx
Requires-Dist: numba
Requires-Dist: pandas>=1.4.0
Requires-Dist: pint
Requires-Dist: pyyaml
Requires-Dist: tqdm
Requires-Dist: xarray>=2023.5.0
Requires-Dist: xmltodict
Requires-Dist: xyzservices
Provides-Extra: lint
Requires-Dist: cffconvert; extra == "lint"
Requires-Dist: click; extra == "lint"
Requires-Dist: ruff; extra == "lint"
Requires-Dist: flynt; extra == "lint"
Requires-Dist: pre-commit; extra == "lint"
Provides-Extra: test
Requires-Dist: pywatershed[lint]; extra == "test"
Requires-Dist: coverage; extra == "test"
Requires-Dist: flaky; extra == "test"
Requires-Dist: filelock; extra == "test"
Requires-Dist: modflow-devtools; extra == "test"
Requires-Dist: pre-commit; extra == "test"
Requires-Dist: pytest!=8.1.0; extra == "test"
Requires-Dist: pytest-cov; extra == "test"
Requires-Dist: pytest-env; extra == "test"
Requires-Dist: pytest-order; extra == "test"
Requires-Dist: pytest-xdist; extra == "test"
Provides-Extra: optional
Requires-Dist: pydot; extra == "optional"
Requires-Dist: geos; extra == "optional"
Requires-Dist: cartopy; extra == "optional"
Requires-Dist: folium; extra == "optional"
Requires-Dist: geopandas; extra == "optional"
Requires-Dist: hvplot; extra == "optional"
Requires-Dist: shapely; extra == "optional"
Requires-Dist: ipython; extra == "optional"
Requires-Dist: jupyter; extra == "optional"
Requires-Dist: jupyterlab; extra == "optional"
Provides-Extra: doc
Requires-Dist: ipython; extra == "doc"
Requires-Dist: jinja2<3.1; extra == "doc"
Requires-Dist: sphinx; extra == "doc"
Requires-Dist: sphinx-book-theme>=0.3.3; extra == "doc"
Requires-Dist: sphinx-autodoc-typehints>=2.2.1; extra == "doc"
Requires-Dist: sphinx-autosummary-accessors; extra == "doc"
Requires-Dist: sphinx-copybutton; extra == "doc"
Provides-Extra: all
Requires-Dist: pywatershed[doc,lint,optional,test]; extra == "all"
